{
    "facebook": "n*2noJ~0Res:s7s}o6-fM\u007f\\+YV[R4*;HnOYD6br-Zz_bfN`'Ha",
    "insta": "#+R;\\UsAtE`0IoS]4qOO_mCUKoh\u007f(q4)?Asx?>G5O<VR8N3WTN",
    "yt": "Fo+xXW,CnvBERwq|5<?VT>t,}fB._-jyx1%qi+Y*><Ct}Yiw(P",
    "reddit": "}Y&/\\enO:7T8@uP>k)xnvf<q&5#f2jn]7LsqN7V@i*hk}Lla|M",
    "google": "m}=aC)&Vi(I\\rKN:0%lhW:~4~{6AvC5U:0T7(3qmO+\u007fn;@)c]I",
    "dc": "Z#{FDt38l]5j2@<OI4CIN=$nd-lu|,\"R+LlHZI$'6a4SW\"Gz2U",
    "viber": ".lAk&&1dlP`yU|,=,M2/FI\\2R/xS\"ylpr6n=E,g|^@^qiNj=w#",
    "spotify": "!!t=pb8B3K1>DoiMS#<F^_AdBZ/Q\\+x^x\\Xf(LC}6W1~1tUQok"
}